{
  "latest_date": "2026-05-18",
  "latest_values": {
    "Shanghai_Composite_Index": 4135.38916015625,
    "CSI_300_Index": 4859.58984375,
    "Shenzhen_Component_Index": 15561.3701171875,
    "ALUMINUM_future": 3518.25,
    "BTC_price": 77082.15625,
    "OIL_price": 101.58999633789062,
    "USD_CNY_exchange_rate": 6.799499988555908,
    "Commodity_Index_ETF": 31.3799991607666,
    "US_Dollar_Index": 98.95600128173828,
    "ETH_price": 2125.159912109375,
    "GOLD_spot_price": 4570.7001953125,
    "LEAN_HOGS_future": 102.9000015258789,
    "COPPER_future": 6.328999996185303,
    "High_Yield_Bond_ETF": 79.54000091552734,
    "LIVE_CATTLE_future": 247.125,
    "GOLD_near_month_future": 4570.7998046875,
    "NATURAL_GAS_future": 3.0230000019073486,
    "PLATINUM_future": 1982.5999755859375,
    "SILVER_future": 78.0199966430664,
    "Long_Term_Treasury_ETF": 83.55999755859375,
    "CORN_future": 477.25,
    "SOYBEANS_future": 1212.0,
    "WHEAT_future": 664.75,
    "SP500_close": 7403.0498046875,
    "NASDAQ_close": 26090.734375,
    "US_10Y_Treasury_Yield": 4.623000144958496,
    "VIX_close": 17.81999969482422,
    "GOLD_basis_spot_vs_near": -0.099609375,
    "China_10Y_Treasury_Yield": 1.7585
  }
}