{
  "latest_date": "2026-02-03",
  "latest_values": {
    "Shanghai_Composite_Index": 4117.9482421875,
    "CSI_300_Index": 4706.33984375,
    "Shenzhen_Component_Index": 14205.8896484375,
    "ALUMINUM_future": 2986.0,
    "BTC_price": 78528.0078125,
    "OIL_price": 61.93000030517578,
    "USD_CNY_exchange_rate": 6.9380998611450195,
    "Commodity_Index_ETF": 23.540000915527344,
    "US_Dollar_Index": 97.44200134277344,
    "ETH_price": 2324.768798828125,
    "GOLD_spot_price": 4825.5,
    "LEAN_HOGS_future": 96.625,
    "COPPER_future": 5.901500225067139,
    "High_Yield_Bond_ETF": 80.7699966430664,
    "LIVE_CATTLE_future": 239.4499969482422,
    "GOLD_near_month_future": 4825.60009765625,
    "NATURAL_GAS_future": 3.240999937057495,
    "PLATINUM_future": 2152.800048828125,
    "SILVER_future": 82.68000030517578,
    "Long_Term_Treasury_ETF": 86.55000305175781,
    "CORN_future": 427.0,
    "SOYBEANS_future": 1062.0,
    "WHEAT_future": 528.75,
    "SP500_close": 6976.43994140625,
    "NASDAQ_close": 23592.107421875,
    "US_10Y_Treasury_Yield": 4.275000095367432,
    "VIX_close": 16.34000015258789,
    "GOLD_basis_spot_vs_near": -0.10009765625,
    "China_10Y_Treasury_Yield": 1.82
  }
}