{
  "latest_date": "2026-02-20",
  "latest_values": {
    "Shanghai_Composite_Index": 4082.072998046875,
    "CSI_300_Index": 4660.41015625,
    "Shenzhen_Component_Index": 14100.1904296875,
    "ALUMINUM_future": 3037.25,
    "BTC_price": 67934.84375,
    "OIL_price": 66.01000213623047,
    "USD_CNY_exchange_rate": 6.903200149536133,
    "Commodity_Index_ETF": 24.43000030517578,
    "US_Dollar_Index": 97.92500305175781,
    "ETH_price": 1952.7705078125,
    "GOLD_spot_price": 5053.2001953125,
    "LEAN_HOGS_future": 83.57499694824219,
    "COPPER_future": 5.752500057220459,
    "High_Yield_Bond_ETF": 80.94000244140625,
    "LIVE_CATTLE_future": 247.75,
    "GOLD_near_month_future": 5053.5,
    "NATURAL_GAS_future": 2.9189999103546143,
    "PLATINUM_future": 2124.800048828125,
    "SILVER_future": 80.7300033569336,
    "Long_Term_Treasury_ETF": 89.62000274658203,
    "CORN_future": 438.5,
    "SOYBEANS_future": 1153.0,
    "WHEAT_future": 570.0,
    "SP500_close": 6861.89013671875,
    "NASDAQ_close": 22682.73046875,
    "US_10Y_Treasury_Yield": 4.074999809265137,
    "VIX_close": 20.25,
    "GOLD_basis_spot_vs_near": -0.2998046875,
    "China_10Y_Treasury_Yield": 1.7899
  }
}