{
  "latest_date": "2026-04-15",
  "latest_values": {
    "Shanghai_Composite_Index": 4027.20947265625,
    "CSI_300_Index": 4685.24658203125,
    "Shenzhen_Component_Index": 14498.455078125,
    "ALUMINUM_future": 3579.5,
    "BTC_price": 74044.7265625,
    "OIL_price": 92.33000183105469,
    "USD_CNY_exchange_rate": 6.8196001052856445,
    "Commodity_Index_ETF": 29.0049991607666,
    "US_Dollar_Index": 98.0479965209961,
    "ETH_price": 2337.72998046875,
    "GOLD_spot_price": 4831.10009765625,
    "LEAN_HOGS_future": 102.125,
    "COPPER_future": 6.085000038146973,
    "High_Yield_Bond_ETF": 80.44499969482422,
    "LIVE_CATTLE_future": 251.5749969482422,
    "GOLD_near_month_future": 4831.10009765625,
    "NATURAL_GAS_future": 2.6110000610351562,
    "PLATINUM_future": 2125.800048828125,
    "SILVER_future": 79.80000305175781,
    "Long_Term_Treasury_ETF": 86.8499984741211,
    "CORN_future": 449.25,
    "SOYBEANS_future": 1167.5,
    "WHEAT_future": 597.75,
    "SP500_close": 6999.64013671875,
    "NASDAQ_close": 23880.71484375,
    "US_10Y_Treasury_Yield": 4.2779998779296875,
    "VIX_close": 17.989999771118164,
    "GOLD_basis_spot_vs_near": 0.0,
    "China_10Y_Treasury_Yield": 1.7809
  }
}