{
  "latest_date": "2025-11-14",
  "latest_values": {
    "Shanghai_Composite_Index": 4029.5009765625,
    "CSI_300_Index": 4702.06982421875,
    "Shenzhen_Component_Index": 13476.51953125,
    "ALUMINUM_future": 2857.5,
    "BTC_price": 97896.609375,
    "OIL_price": 59.599998474121094,
    "USD_CNY_exchange_rate": 7.0929999351501465,
    "Commodity_Index_ETF": 22.920000076293945,
    "US_Dollar_Index": 99.16799926757812,
    "ETH_price": 3181.901611328125,
    "GOLD_spot_price": 4206.2998046875,
    "LEAN_HOGS_future": 78.17500305175781,
    "COPPER_future": 5.072000026702881,
    "High_Yield_Bond_ETF": 80.19999694824219,
    "LIVE_CATTLE_future": 218.875,
    "GOLD_near_month_future": 4206.2998046875,
    "NATURAL_GAS_future": 4.618000030517578,
    "PLATINUM_future": 1607.9000244140625,
    "SILVER_future": 52.95000076293945,
    "Long_Term_Treasury_ETF": 89.37999725341797,
    "CORN_future": 441.0,
    "SOYBEANS_future": 1149.0,
    "WHEAT_future": 554.0,
    "SP500_close": 6737.490234375,
    "NASDAQ_close": 22870.359375,
    "US_10Y_Treasury_Yield": 4.111999988555908,
    "VIX_close": 20.0,
    "GOLD_basis_spot_vs_near": 0.0,
    "China_10Y_Treasury_Yield": 1.8126
  }
}