{
  "latest_date": "2025-10-01",
  "latest_values": {
    "Shanghai_Composite_Index": 3882.77734375,
    "CSI_300_Index": 4640.693359375,
    "Shenzhen_Component_Index": 13526.5087890625,
    "ALUMINUM_future": 2612.75,
    "BTC_price": 114156.1328125,
    "OIL_price": 62.560001373291016,
    "USD_CNY_exchange_rate": 7.118500232696533,
    "Commodity_Index_ETF": 22.530000686645508,
    "US_Dollar_Index": 97.88200378417969,
    "ETH_price": 4146.375,
    "GOLD_spot_price": 3891.39990234375,
    "LEAN_HOGS_future": 99.69999694824219,
    "COPPER_future": 4.869999885559082,
    "High_Yield_Bond_ETF": 81.19000244140625,
    "LIVE_CATTLE_future": 234.8000030517578,
    "GOLD_near_month_future": 3891.199951171875,
    "NATURAL_GAS_future": 3.3369998931884766,
    "PLATINUM_future": 1584.9000244140625,
    "SILVER_future": 46.91999816894531,
    "Long_Term_Treasury_ETF": 89.37000274658203,
    "CORN_future": 415.25,
    "SOYBEANS_future": 999.75,
    "WHEAT_future": 506.5,
    "SP500_close": 6688.4599609375,
    "NASDAQ_close": 22660.009765625,
    "US_10Y_Treasury_Yield": 4.1479997634887695,
    "VIX_close": 16.280000686645508,
    "GOLD_basis_spot_vs_near": 0.199951171875,
    "China_10Y_Treasury_Yield": 1.8605
  }
}