{
  "latest_date": "2026-07-02",
  "latest_values": {
    "Shanghai_Composite_Index": 4028.90380859375,
    "CSI_300_Index": 4812.2958984375,
    "Shenzhen_Component_Index": 15498.810546875,
    "ALUMINUM_future": 3269.75,
    "BTC_price": 61793.171875,
    "OIL_price": 67.86000061035156,
    "USD_CNY_exchange_rate": 6.793600082397461,
    "Commodity_Index_ETF": 26.53499984741211,
    "US_Dollar_Index": 100.72799682617188,
    "ETH_price": 1707.5,
    "GOLD_spot_price": 4148.2998046875,
    "LEAN_HOGS_future": 96.82499694824219,
    "COPPER_future": 6.21750020980835,
    "High_Yield_Bond_ETF": 79.7750015258789,
    "LIVE_CATTLE_future": 241.875,
    "GOLD_near_month_future": 4148.60009765625,
    "NATURAL_GAS_future": 3.184999942779541,
    "PLATINUM_future": 1639.800048828125,
    "SILVER_future": 62.290000915527344,
    "Long_Term_Treasury_ETF": 85.46499633789062,
    "CORN_future": 445.5,
    "SOYBEANS_future": 1156.5,
    "WHEAT_future": 606.0,
    "SP500_close": 7533.5,
    "NASDAQ_close": 26213.31640625,
    "US_10Y_Treasury_Yield": 4.474999904632568,
    "VIX_close": 15.989999771118164,
    "GOLD_basis_spot_vs_near": -0.30029296875,
    "China_10Y_Treasury_Yield": 1.741
  }
}