{
  "latest_date": "2026-04-06",
  "latest_values": {
    "Shanghai_Composite_Index": 3880.096923828125,
    "CSI_300_Index": 4440.7900390625,
    "Shenzhen_Component_Index": 13352.900390625,
    "ALUMINUM_future": 3417.75,
    "BTC_price": 69713.359375,
    "OIL_price": 111.45999908447266,
    "USD_CNY_exchange_rate": 6.8850998878479,
    "Commodity_Index_ETF": 29.399999618530273,
    "US_Dollar_Index": 99.99800109863281,
    "ETH_price": 2166.2431640625,
    "GOLD_spot_price": 4696.2998046875,
    "LEAN_HOGS_future": 107.2249984741211,
    "COPPER_future": 5.59250020980835,
    "High_Yield_Bond_ETF": 79.63999938964844,
    "LIVE_CATTLE_future": 246.75,
    "GOLD_near_month_future": 4697.0,
    "NATURAL_GAS_future": 2.828000068664551,
    "PLATINUM_future": 1978.5999755859375,
    "SILVER_future": 72.58999633789062,
    "Long_Term_Treasury_ETF": 86.6614990234375,
    "CORN_future": 452.75,
    "SOYBEANS_future": 1166.75,
    "WHEAT_future": 592.5,
    "SP500_close": 6600.31982421875,
    "NASDAQ_close": 21966.953125,
    "US_10Y_Treasury_Yield": 4.328999996185303,
    "VIX_close": 24.149999618530273,
    "GOLD_basis_spot_vs_near": -0.7001953125,
    "China_10Y_Treasury_Yield": 1.8199
  }
}