{
  "latest_date": "2026-06-17",
  "latest_values": {
    "Shanghai_Composite_Index": 4108.076171875,
    "CSI_300_Index": 4931.38623046875,
    "Shenzhen_Component_Index": 15880.951171875,
    "ALUMINUM_future": 3416.75,
    "BTC_price": 65246.2890625,
    "OIL_price": 76.80000305175781,
    "USD_CNY_exchange_rate": 6.756999969482422,
    "Commodity_Index_ETF": 28.0,
    "US_Dollar_Index": 99.69499969482422,
    "ETH_price": 1759.75,
    "GOLD_spot_price": 4367.2001953125,
    "LEAN_HOGS_future": 95.9749984741211,
    "COPPER_future": 6.486000061035156,
    "High_Yield_Bond_ETF": 80.0199966430664,
    "LIVE_CATTLE_future": 248.6750030517578,
    "GOLD_near_month_future": 4367.10009765625,
    "NATURAL_GAS_future": 3.1559998989105225,
    "PLATINUM_future": 1787.199951171875,
    "SILVER_future": 70.45999908447266,
    "Long_Term_Treasury_ETF": 86.33000183105469,
    "CORN_future": 418.5,
    "SOYBEANS_future": 1151.25,
    "WHEAT_future": 616.75,
    "SP500_close": 7508.990234375,
    "NASDAQ_close": 26337.953125,
    "US_10Y_Treasury_Yield": 4.440999984741211,
    "VIX_close": 16.84000015258789,
    "GOLD_basis_spot_vs_near": 0.10009765625,
    "China_10Y_Treasury_Yield": 1.727
  }
}