[
  {
    "code": "002938",
    "name": "",
    "analysis_result": {
      "code": "002938",
      "name": "",
      "should_exclude": true,
      "reason": "近期明显下跌走势",
      "analysis": "股票价格在最近一个月（从2025-11-04的51.79元跌至2025-11-17的44.38元，跌幅约14.3%）呈现清晰、持续的下跌趋势，且没有明显的企稳迹象。"
    }
  },
  {
    "code": "000988",
    "name": "",
    "analysis_result": {
      "code": "000988",
      "name": "",
      "should_exclude": true,
      "reason": "涨幅巨大，炒作接近泡沫",
      "analysis": "股票价格在过去半年内经历了非常巨大的涨幅（从2025年5月的41.73元最高涨至92.48元，涨幅超过120%），存在估值过高和泡沫风险。近期价格虽有所回落，但其整体走势符合过度炒作的特征。"
    }
  },
  {
    "code": "300570",
    "name": "",
    "analysis_result": {
      "code": "300570",
      "name": "",
      "should_exclude": true,
      "reason": "涨幅巨大，炒作接近泡沫",
      "analysis": "股票价格在过去半年内经历了非常巨大的涨幅（从2025年5月的69.58元最高涨至142.14元，涨幅超过100%），存在估值过高和泡沫风险。尽管近期价格有所回落，但其整体走势符合过度炒作的特征。"
    }
  },
  {
    "code": "600309",
    "name": "",
    "analysis_result": {
      "code": "600309",
      "name": "",
      "should_exclude": false,
      "reason": "",
      "analysis": "股票价格在近期未出现明显下跌走势，过去半年也未出现巨大涨幅，不符合排除标准。财务报表数据完整。"
    }
  },
  {
    "code": "002648",
    "name": "",
    "analysis_result": {
      "code": "002648",
      "name": "",
      "should_exclude": false,
      "reason": "",
      "analysis": "股票价格在近期和过去半年均未出现明显下跌走势或巨大涨幅，不符合排除标准。财务报表数据完整。"
    }
  },
  {
    "code": "600961",
    "name": "",
    "analysis_result": {
      "should_exclude": true,
      "reason": "分析失败",
      "analysis": "未能从AI获取对此股票的有效分析。请检查日志中AI的原始响应。"
    }
  },
  {
    "code": "002536",
    "name": "",
    "analysis_result": {
      "should_exclude": true,
      "reason": "分析失败",
      "analysis": "未能从AI获取对此股票的有效分析。请检查日志中AI的原始响应。"
    }
  },
  {
    "code": "002991",
    "name": "",
    "analysis_result": {
      "code": "002991",
      "name": "",
      "should_exclude": false,
      "reason": "",
      "analysis": "股票价格在近期和过去半年均未出现明显下跌走势或巨大涨幅，不符合排除标准。财务报表数据完整。"
    }
  },
  {
    "code": "603067",
    "name": "",
    "analysis_result": {
      "code": "603067",
      "name": "",
      "should_exclude": true,
      "reason": "涨幅巨大，炒作接近泡沫",
      "analysis": "股票价格在过去一个月内（从2025年10月底的19.81元飙升至11月初的33.20元，涨幅超过67%）经历了非常巨大的短期涨幅，存在明显的炒作和泡沫风险。"
    }
  },
  {
    "code": "002064",
    "name": "",
    "analysis_result": {
      "code": "002064",
      "name": "",
      "should_exclude": false,
      "reason": "",
      "analysis": "股票价格在近期和过去半年均未出现明显下跌走势或巨大涨幅，不符合排除标准。财务报表数据完整。"
    }
  }
]