[
  {
    "code": "002938",
    "name": "",
    "analysis_result": {
      "code": "002938",
      "name": "",
      "should_exclude": true,
      "reason": "涨幅巨大，炒作接近泡沫",
      "analysis": "该股票在过去半年内（从2025-04-24的28.285到2025-10-24的52.84）价格上涨了约86.74%，涨幅巨大，存在炒作接近泡沫的风险。近期走势未构成明显下跌趋势（近1个月跌幅约8.39%）。"
    }
  },
  {
    "code": "601138",
    "name": "",
    "analysis_result": {
      "code": "601138",
      "name": "",
      "should_exclude": true,
      "reason": "涨幅巨大，炒作接近泡沫",
      "analysis": "该股票在过去半年内（从2025-04-24的17.575到2025-10-24的67.25）价格暴涨约282.67%，涨幅极其巨大，存在严重的炒作和泡沫风险。近期股价略有上涨，不符合近期明显下跌走势的排除标准。"
    }
  },
  {
    "code": "000988",
    "name": "",
    "analysis_result": {
      "code": "000988",
      "name": "",
      "should_exclude": true,
      "reason": "近期明显下跌走势",
      "analysis": "该股票在近期（从2025-09-19的91.12到2025-10-24的81.019）价格下跌了约11.08%，表现出清晰的下跌趋势，且在期间未见明显企稳迹象。过去半年内涨幅巨大（约109.77%）。"
    }
  },
  {
    "code": "301489",
    "name": "",
    "analysis_result": {
      "code": "301489",
      "name": "",
      "should_exclude": true,
      "reason": "近期明显下跌走势",
      "analysis": "该股票在近期（从2025-09-24的273.36到2025-10-24的232.0）价格下跌了约15.1%，存在明显的下跌走势，尽管近期有小幅反弹，但未显示企稳。过去半年内涨幅巨大（约467.8%）。"
    }
  },
  {
    "code": "603009",
    "name": "",
    "analysis_result": {
      "should_exclude": true,
      "reason": "分析失败",
      "analysis": "未能从AI获取对此股票的有效分析。请检查日志中AI的原始响应。"
    }
  },
  {
    "code": "600309",
    "name": "",
    "analysis_result": {
      "code": "600309",
      "name": "",
      "should_exclude": true,
      "reason": "近期明显下跌走势",
      "analysis": "该股票在近期（从2025-09-19的55.569到2025-10-24的49.93）价格下跌了约10.14%，符合近期明显下跌走势的排除标准，且没有明显的企稳迹象。过去半年内涨幅约14.59%，未达巨大涨幅标准。"
    }
  },
  {
    "code": "600301",
    "name": "",
    "analysis_result": {
      "code": "600301",
      "name": "",
      "should_exclude": true,
      "reason": "近期明显下跌走势",
      "analysis": "该股票在近期（从2025-09-19的30.969到2025-10-24的27.35）价格下跌了约11.68%，表现出清晰的下跌趋势，且未见企稳迹象。过去半年内涨幅约37.37%，未达巨大涨幅标准。"
    }
  },
  {
    "code": "600900",
    "name": "",
    "analysis_result": {
      "code": "600900",
      "name": "",
      "should_exclude": false,
      "reason": "",
      "analysis": "股价在近期（近1个月涨幅约3.63%）和过去半年内（近6个月跌幅约1.92%）走势平稳，未出现明显下跌或巨大涨幅，不符合排除标准。"
    }
  },
  {
    "code": "002991",
    "name": "",
    "analysis_result": {
      "code": "002991",
      "name": "",
      "should_exclude": false,
      "reason": "",
      "analysis": "股价在近期（近1个月跌幅约2.06%）和过去半年内（近6个月跌幅约22.32%）未出现明显下跌或巨大涨幅，不符合排除标准。"
    }
  },
  {
    "code": "601128",
    "name": "",
    "analysis_result": {
      "should_exclude": true,
      "reason": "分析失败",
      "analysis": "未能从AI获取对此股票的有效分析。请检查日志中AI的原始响应。"
    }
  }
]