[
  {
    "code": "600050",
    "name": "",
    "analysis_result": {
      "code": "600050",
      "name": "",
      "should_exclude": true,
      "reason": "近期明显下跌走势",
      "analysis": "该股票在过去一个月内，从2025年9月10日的约5.76元下跌至2025年10月10日的约5.53元，呈现约4%的明确下跌趋势，且近期高点后未见企稳迹象。近半年涨幅约3%，未达泡沫化程度，但短期下行风险显现。"
    }
  },
  {
    "code": "000988",
    "name": "",
    "analysis_result": {
      "code": "000988",
      "name": "",
      "should_exclude": true,
      "reason": "涨幅巨大，炒作接近泡沫",
      "analysis": "该股票在过去六个月内累计上涨约130%，涨幅巨大，估值可能已过高，存在显著的泡沫化风险，虽然近期从9月末高点有所回调，但整体炒作风险仍存，不适宜纳入观察列表。"
    }
  },
  {
    "code": "603606",
    "name": "",
    "analysis_result": {
      "code": "603606",
      "name": "",
      "should_exclude": false,
      "reason": null,
      "analysis": "该股票近半年上涨约44.3%，涨幅虽不小，但尚未达到巨大泡沫化风险的程度。近一个月股价波动较大，但整体未呈现清晰、持续的下跌趋势，故不予排除。"
    }
  },
  {
    "code": "002938",
    "name": "",
    "analysis_result": {
      "code": "002938",
      "name": "",
      "should_exclude": true,
      "reason": "涨幅巨大，炒作接近泡沫",
      "analysis": "该股票在过去六个月内累计上涨约100%，涨幅巨大，存在潜在的估值过高和泡沫风险。同时，近期从9月高点66.64元下跌至10月10日的54.15元，短期跌幅达18.8%，下跌趋势明显，不适宜纳入观察列表。"
    }
  },
  {
    "code": "002536",
    "name": "",
    "analysis_result": {
      "code": "002536",
      "name": "",
      "should_exclude": true,
      "reason": "涨幅巨大，炒作接近泡沫",
      "analysis": "该股票在过去六个月内累计上涨约97%，涨幅巨大，估值可能过高，存在明显的泡沫风险。此外，近期从9月高点28.68元下跌至10月10日的24.51元，短期跌幅达14.5%，下跌趋势清晰，不适宜纳入观察列表。"
    }
  },
  {
    "code": "300763",
    "name": "",
    "analysis_result": {
      "code": "300763",
      "name": "",
      "should_exclude": true,
      "reason": "涨幅巨大，炒作接近泡沫",
      "analysis": "该股票在过去六个月内累计上涨约71.7%，涨幅较为巨大，结合其波动性，存在一定的炒作和估值过高风险，不适宜纳入观察列表。近一个月股价虽有回调，但整体趋势并非持续下跌。"
    }
  },
  {
    "code": "600961",
    "name": "",
    "analysis_result": {
      "code": "600961",
      "name": "",
      "should_exclude": false,
      "reason": null,
      "analysis": "该股票近半年涨幅约1.73%，远未达到巨大涨幅和泡沫化程度。近一个月股价波动后整体呈现小幅上涨，未有明显下跌走势，故不予排除。"
    }
  },
  {
    "code": "002648",
    "name": "",
    "analysis_result": {
      "should_exclude": true,
      "reason": "分析失败",
      "analysis": "未能从AI获取对此股票的有效分析。请检查日志中AI的原始响应。"
    }
  },
  {
    "code": "000683",
    "name": "",
    "analysis_result": {
      "code": "000683",
      "name": "",
      "should_exclude": false,
      "reason": null,
      "analysis": "该股票近半年上涨约32.92%，涨幅尚可，未达巨大涨幅或泡沫化风险。近一个月股价在高位震荡，但未出现清晰、持续的下跌趋势，故不予排除。"
    }
  },
  {
    "code": "002859",
    "name": "",
    "analysis_result": {
      "code": "002859",
      "name": "",
      "should_exclude": true,
      "reason": "涨幅巨大，炒作接近泡沫",
      "analysis": "该股票在过去六个月内累计上涨约85.65%，涨幅巨大，存在较高的估值过高和泡沫风险，不适宜纳入观察列表。尽管近一个月总体小幅上涨，但从9月中旬的33.86元高点已回调至31.97元，短期波动较大。"
    }
  }
]