[
  {
    "code": "002938",
    "name": "",
    "analysis_result": {
      "code": "002938",
      "name": "",
      "should_exclude": false,
      "reason": "",
      "analysis": "近半年股价上涨约50%，近一月虽有波动但无明显持续下跌趋势。财务报表显示营收和净利润近年有波动，但整体保持盈利且2024年有所回升，未达到涨幅巨大接近泡沫的程度。"
    }
  },
  {
    "code": "601138",
    "name": "",
    "analysis_result": {
      "code": "601138",
      "name": "",
      "should_exclude": true,
      "reason": "涨幅巨大，炒作接近泡沫",
      "analysis": "近半年股价涨幅超过200%（从约20.5元涨至61.9元），表现出非常巨大的涨幅，存在明显的泡沫风险和炒作迹象。"
    }
  },
  {
    "code": "002536",
    "name": "",
    "analysis_result": {
      "code": "002536",
      "name": "",
      "should_exclude": false,
      "reason": "",
      "analysis": "近半年股价上涨约53%，虽然涨幅显著，但其盈利能力在2023-2024年有所恢复和增长，未显示近期明显下跌走势，也未达到涨幅巨大接近泡沫的程度。"
    }
  },
  {
    "code": "603063",
    "name": "",
    "analysis_result": {
      "code": "603063",
      "name": "",
      "should_exclude": false,
      "reason": "",
      "analysis": "近半年股价略有上涨，近一月价格虽有波动但未形成清晰、持续的下跌趋势；然而2024年净利润出现大幅亏损且营收大幅下滑，但根据规定，财务状况不佳并非排除标准，不应被排除。"
    }
  },
  {
    "code": "600519",
    "name": "",
    "analysis_result": {
      "code": "600519",
      "name": "",
      "should_exclude": false,
      "reason": "",
      "analysis": "净利润和EPS在2021年后出现断崖式下跌，与营收持续增长的趋势严重背离，这使得核心盈利能力数据不具备可比性或存在重大未披露信息，可能存在数据解读或记录不完整问题，建议用户自行核实相关财务报表。"
    }
  },
  {
    "code": "600309",
    "name": "",
    "analysis_result": {
      "code": "600309",
      "name": "",
      "should_exclude": false,
      "reason": "",
      "analysis": "尽管营收持续增长，但净利润和EPS却呈现下滑趋势，表明可能存在利润率压力、成本上升或非经常性损益影响，使得核心盈利数据解读存在复杂性，建议用户自行核实相关财务报表。"
    }
  },
  {
    "code": "002859",
    "name": "",
    "analysis_result": {
      "code": "002859",
      "name": "",
      "should_exclude": false,
      "reason": "",
      "analysis": "近半年股价上涨约57%，但其营收和净利润波动较大且2024年净利润有所下滑，未显示近期明显下跌走势，也未达到涨幅巨大接近泡沫的程度。"
    }
  },
  {
    "code": "600732",
    "name": "",
    "analysis_result": {
      "code": "600732",
      "name": "",
      "should_exclude": false,
      "reason": "",
      "analysis": "近半年股价上涨约14%，未显示近期明显下跌走势或涨幅巨大；但公司在2021年和2024年出现巨额亏损，且营收和净利润高度波动，不符合排除标准。"
    }
  },
  {
    "code": "600301",
    "name": "",
    "analysis_result": {
      "should_exclude": true,
      "reason": "分析失败",
      "analysis": "未能从AI获取对此股票的有效分析。请检查日志中AI的原始响应。"
    }
  },
  {
    "code": "600050",
    "name": "",
    "analysis_result": {
      "should_exclude": true,
      "reason": "分析失败",
      "analysis": "未能从AI获取对此股票的有效分析。请检查日志中AI的原始响应。"
    }
  }
]