[
  {
    "code": "601138",
    "name": "",
    "analysis_result": {
      "code": "601138",
      "name": "",
      "should_exclude": true,
      "reason": "涨幅巨大，炒作接近泡沫",
      "analysis": "该股票在过去半年内表现出惊人的涨幅，从2025年4月17日的16.76元飙升至2025年10月17日的60.01元，涨幅高达257%。尽管近期股价有所波动，但如此巨大的短期涨幅已显著抬高估值，存在明显的炒作和潜在泡沫风险。"
    }
  },
  {
    "code": "002938",
    "name": "",
    "analysis_result": {
      "code": "002938",
      "name": "",
      "should_exclude": true,
      "reason": "近期明显下跌走势",
      "analysis": "该股票在过去一个月内表现出清晰且持续的下跌趋势。从2025年9月22日的高点63.45元，股价一路下探至2025年10月17日的46.75元，跌幅超过26%，期间虽有小幅反弹，但未能形成有效企稳，下跌走势显著。"
    }
  },
  {
    "code": "002859",
    "name": "",
    "analysis_result": {
      "code": "002859",
      "name": "",
      "should_exclude": true,
      "reason": "近期明显下跌走势",
      "analysis": "该股票在过去一个月内呈现明显下跌趋势。自2025年9月30日高点33.51元以来，股价持续下行，截至2025年10月17日收盘29.96元，跌幅超过10%，近期缺乏明确的企稳迹象。"
    }
  },
  {
    "code": "002536",
    "name": "",
    "analysis_result": {
      "should_exclude": true,
      "reason": "分析失败",
      "analysis": "未能从AI获取对此股票的有效分析。请检查日志中AI的原始响应。"
    }
  },
  {
    "code": "600460",
    "name": "",
    "analysis_result": {
      "code": "600460",
      "name": "",
      "should_exclude": true,
      "reason": "近期明显下跌走势",
      "analysis": "该股票在最近一周内经历快速下跌。从2025年10月13日的高点33.36元，股价在短短4个交易日内跌至2025年10月17日的29.94元，跌幅约10%，下跌趋势清晰且没有企稳迹象。"
    }
  },
  {
    "code": "600301",
    "name": "",
    "analysis_result": {
      "code": "600301",
      "name": "",
      "should_exclude": true,
      "reason": "近期明显下跌走势",
      "analysis": "该股票在过去一周内出现大幅且持续的下跌。从2025年10月9日的高点34.52元，股价快速滑落至2025年10月17日的27.82元，跌幅接近20%，近期下跌趋势非常明显且无企稳迹象。"
    }
  },
  {
    "code": "600309",
    "name": "",
    "analysis_result": {
      "should_exclude": true,
      "reason": "分析失败",
      "analysis": "未能从AI获取对此股票的有效分析。请检查日志中AI的原始响应。"
    }
  },
  {
    "code": "603063",
    "name": "",
    "analysis_result": {
      "should_exclude": true,
      "reason": "分析失败",
      "analysis": "未能从AI获取对此股票的有效分析。请检查日志中AI的原始响应。"
    }
  },
  {
    "code": "600050",
    "name": "",
    "analysis_result": {
      "code": "600050",
      "name": "",
      "should_exclude": false,
      "reason": null,
      "analysis": "该股票在过去一个月及半年内价格波动幅度相对较小，未观察到清晰、持续的下跌趋势，也未经历巨大涨幅引发泡沫风险，不符合任何排除标准。"
    }
  },
  {
    "code": "603606",
    "name": "",
    "analysis_result": {
      "should_exclude": true,
      "reason": "分析失败",
      "analysis": "未能从AI获取对此股票的有效分析。请检查日志中AI的原始响应。"
    }
  }
]