[
  {
    "code": "300308",
    "name": "",
    "analysis_result": {
      "code": "300308",
      "name": "",
      "should_exclude": true,
      "reason": "涨幅巨大，炒作接近泡沫",
      "analysis": "该股票在过去半年内涨幅超过500%，股价从80元飙升至494元，存在显著的估值过高和泡沫风险。"
    }
  },
  {
    "code": "601138",
    "name": "",
    "analysis_result": {
      "code": "601138",
      "name": "",
      "should_exclude": true,
      "reason": "涨幅巨大，炒作接近泡沫",
      "analysis": "该股票在过去半年内涨幅接近300%，股价从17元涨至67元，存在显著的估值过高和泡沫风险。"
    }
  },
  {
    "code": "603009",
    "name": "",
    "analysis_result": {
      "code": "603009",
      "name": "",
      "should_exclude": true,
      "reason": "近期明显下跌走势",
      "analysis": "该股票在过去一个月内呈现出清晰、持续的下跌趋势，股价从9月底的58元左右下跌至目前的49元，没有明显的企稳迹象。"
    }
  },
  {
    "code": "603993",
    "name": "",
    "analysis_result": {
      "code": "603993",
      "name": "",
      "should_exclude": true,
      "reason": "涨幅巨大，炒作接近泡沫",
      "analysis": "该股票在过去半年内涨幅超过145%，股价从6.8元飙升至16.7元，存在显著的估值过高和泡沫风险。"
    }
  },
  {
    "code": "600309",
    "name": "",
    "analysis_result": {
      "code": "600309",
      "name": "",
      "should_exclude": true,
      "reason": "近期明显下跌走势",
      "analysis": "该股票在过去一个月内呈现出清晰、持续的下跌趋势，股价从9月底的63元左右下跌至目前的61元，没有明显的企稳迹象。"
    }
  },
  {
    "code": "002938",
    "name": "",
    "analysis_result": {
      "code": "002938",
      "name": "",
      "should_exclude": true,
      "reason": "涨幅巨大，炒作接近泡沫",
      "analysis": "该股票在过去半年内涨幅超过109%，股价从38元飙升至81元，存在显著的估值过高和泡沫风险。"
    }
  },
  {
    "code": "000988",
    "name": "",
    "analysis_result": {
      "code": "000988",
      "name": "",
      "should_exclude": true,
      "reason": "近期明显下跌走势",
      "analysis": "该股票在过去一个月内呈现出清晰、持续的下跌趋势，股价从9月底的90元左右下跌至目前的81元，没有明显的企稳迹象。"
    }
  },
  {
    "code": "300570",
    "name": "",
    "analysis_result": {
      "code": "300570",
      "name": "",
      "should_exclude": true,
      "reason": "涨幅巨大，炒作接近泡沫",
      "analysis": "该股票在过去半年内涨幅超过625%，股价从14元飙升至108元，存在极其显著的估值过高和泡沫风险。"
    }
  },
  {
    "code": "002536",
    "name": "",
    "analysis_result": {
      "code": "002536",
      "name": "",
      "should_exclude": true,
      "reason": "涨幅巨大，炒作接近泡沫",
      "analysis": "该股票在过去半年内涨幅超过50%，股价从14.9元涨至22.5元，存在估值过高和泡沫风险。"
    }
  },
  {
    "code": "301029",
    "name": "",
    "analysis_result": {
      "code": "301029",
      "name": "",
      "should_exclude": true,
      "reason": "近期明显下跌走势",
      "analysis": "该股票在过去一个月内呈现出清晰、持续的下跌趋势，股价从9月底的31元左右下跌至目前的27元，没有明显的企稳迹象。"
    }
  }
]